README.rst
setup.py
scientpyfic/API.py
scientpyfic/__init__.py
scientpyfic/agents.txt
scientpyfic/client.py
scientpyfic/exception.py
scientpyfic/random_user_agent.py
scientpyfic.egg-info/PKG-INFO
scientpyfic.egg-info/SOURCES.txt
scientpyfic.egg-info/dependency_links.txt
scientpyfic.egg-info/requires.txt
scientpyfic.egg-info/top_level.txt
scientpyfic.egg-info/zip-safe
scientpyfic/module/__init__.py
scientpyfic/module/environment/__init__.py
scientpyfic/module/environment/environment.py
scientpyfic/module/environment/earth_climate/__init__.py
scientpyfic/module/environment/earth_climate/atmosphere.py
scientpyfic/module/environment/earth_climate/business_industry.py
scientpyfic/module/environment/earth_climate/earth_climate.py
scientpyfic/module/environment/earth_climate/earth_science.py
scientpyfic/module/environment/earth_climate/education_learning.py
scientpyfic/module/environment/earth_climate/environmental_issues.py
scientpyfic/module/environment/earth_climate/environmental_science.py
scientpyfic/module/environment/earth_climate/natural_disaster.py
scientpyfic/module/environment/earth_climate/severe_weather.py
scientpyfic/module/environment/fossils_ruins/__init__.py
scientpyfic/module/environment/fossils_ruins/anthropology.py
scientpyfic/module/environment/fossils_ruins/archaeology.py
scientpyfic/module/environment/fossils_ruins/evolution.py
scientpyfic/module/environment/fossils_ruins/fossils_ruins.py
scientpyfic/module/environment/fossils_ruins/paleontology.py
scientpyfic/module/environment/plants_animals/__init__.py
scientpyfic/module/environment/plants_animals/agriculture_food.py
scientpyfic/module/environment/plants_animals/animal.py
scientpyfic/module/environment/plants_animals/business_industry.py
scientpyfic/module/environment/plants_animals/ecology.py
scientpyfic/module/environment/plants_animals/education_learning.py
scientpyfic/module/environment/plants_animals/life_science.py
scientpyfic/module/environment/plants_animals/microbes_more.py
scientpyfic/module/environment/plants_animals/plants_animals.py
scientpyfic/module/health/__init__.py
scientpyfic/module/health/health.py
scientpyfic/module/health/health_medicine/__init__.py
