Metadata-Version: 1.1
Name: scientpyfic
Version: 0.0.3
Summary: Latest science news from ScienceDaily.
Home-page: https://github.com/monzita/scientpyfic
Author: Monika Ilieva
Author-email: hidden@hidden.com
License: MIT
Keywords: scientpyfic science daily python beautifulsoup
Platform: UNKNOWN
Classifier: Development Status :: 3 - Alpha
Classifier: Intended Audience :: Science/Research
Classifier: Intended Audience :: Developers
Classifier: Intended Audience :: Education
Classifier: License :: OSI Approved :: MIT License
Classifier: Programming Language :: Python :: 3.5
Classifier: Programming Language :: Python :: 3.6
Classifier: Programming Language :: Python :: 3.7
Classifier: Programming Language :: Python :: 3 :: Only
Classifier: Topic :: Utilities
